guidelinely/__init__.py
guidelinely/auth.py
guidelinely/cache.py
guidelinely/client.py
guidelinely/exceptions.py
guidelinely/models.py
guidelinely/py.typed
guidelinely-1.0.36.dist-info/licenses/LICENSE
guidelinely-1.0.36.dist-info/METADATA
guidelinely-1.0.36.dist-info/WHEEL
guidelinely-1.0.36.dist-info/top_level.txt
guidelinely-1.0.36.dist-info/RECORD
