Metadata-Version: 2.4
Name: guidelinely
Version: 1.0.36
Summary: Python client for the Guidelinely Environmental Guidelines API
Author-email: Michael Davison <michael.davison@gmail.com>
License-Expression: MIT
Project-URL: Homepage, https://github.com/mpdavison/envguidelines-py
Project-URL: Documentation, https://guidelinely.1681248.com/docs
Project-URL: Repository, https://github.com/mpdavison/envguidelines-py
Project-URL: Bug Tracker, https://github.com/mpdavison/envguidelines-py/issues
Keywords: environmental,guidelines,api,water quality,soil,sediment
Classifier: Development Status :: 3 - Alpha
Classifier: Intended Audience :: Science/Research
Classifier: Programming Language :: Python :: 3
Classifier: Programming Language :: Python :: 3.9
Classifier: Programming Language :: Python :: 3.10
Classifier: Programming Language :: Python :: 3.11
Classifier: Programming Language :: Python :: 3.12
Classifier: Topic :: Scientific/Engineering
Requires-Python: >=3.9
License-File: LICENSE
Requires-Dist: httpx>=0.25.0
Requires-Dist: pydantic>=2.0.0
Requires-Dist: diskcache>=5.6.0
Requires-Dist: python-dotenv>=1.0.0
Provides-Extra: dev
Requires-Dist: pytest>=7.0.0; extra == "dev"
Requires-Dist: pytest-asyncio>=0.21.0; extra == "dev"
Requires-Dist: pytest-cov>=4.0.0; extra == "dev"
Requires-Dist: pytest-httpx>=0.30.0; extra == "dev"
Requires-Dist: responses>=0.23.0; extra == "dev"
Requires-Dist: black>=23.0.0; extra == "dev"
Requires-Dist: mypy>=1.0.0; extra == "dev"
Requires-Dist: ruff>=0.1.0; extra == "dev"
Requires-Dist: pre-commit>=3.0.0; extra == "dev"
Dynamic: license-file
